trimeshpy/__init__.py
trimeshpy/io.py
trimeshpy/trimesh_class.py
trimeshpy/trimesh_vtk.py
trimeshpy/trimeshflow_class.py
trimeshpy/trimeshflow_vtk.py
trimeshpy/vtk_util.py
trimeshpy/data/__init__.py
trimeshpy/data/brain_mesh/100307_a2009s_lh.annot
trimeshpy/data/brain_mesh/100307_a2009s_rh.annot
trimeshpy/data/brain_mesh/100307_aparc_lh.annot
trimeshpy/data/brain_mesh/100307_aparc_rh.annot
trimeshpy/data/brain_mesh/100307_t1.nii.gz
trimeshpy/data/brain_mesh/100307_wmparc.nii.gz
trimeshpy/data/brain_mesh/__init__.py
trimeshpy/data/out/__init__.py
trimeshpy/data/test_mesh/__init__.py
trimeshpy/data/test_mesh/bunny.obj
trimeshpy/data/test_mesh/cube_simple.obj
trimeshpy/data/test_mesh/cube_tri.npy
trimeshpy/data/test_mesh/cube_vts.npy
trimeshpy/data/test_mesh/planar_tris.npy
trimeshpy/data/test_mesh/planar_tris_multi.npy
trimeshpy/data/test_mesh/planar_vts_2d.npy
trimeshpy/data/test_mesh/planar_vts_4d.npy
trimeshpy/data/test_mesh/sphere.obj
trimeshpy/data/test_mesh/spot.obj
trimeshpy/data/test_mesh/torus.obj
trimeshpy/math/__init__.py
trimeshpy/math/angle.py
trimeshpy/math/area.py
trimeshpy/math/curvature.py
trimeshpy/math/geo_diff.py
trimeshpy/math/matrix.py
trimeshpy/math/mesh_global.py
trimeshpy/math/mesh_map.py
trimeshpy/math/normal.py
trimeshpy/math/remeshing.py
trimeshpy/math/smooth.py
trimeshpy/math/transfo.py
trimeshpy/math/util.py
trimeshpy-0.0.4.dist-info/LICENSE
trimeshpy-0.0.4.dist-info/METADATA
trimeshpy-0.0.4.dist-info/WHEEL
trimeshpy-0.0.4.dist-info/top_level.txt
trimeshpy-0.0.4.dist-info/RECORD
